mailtm/__init__.py
mailtm/client.py
mailtm/types.py
mailtm_python-0.1.0.dist-info/LICENSE
mailtm_python-0.1.0.dist-info/METADATA
mailtm_python-0.1.0.dist-info/WHEEL
mailtm_python-0.1.0.dist-info/top_level.txt
mailtm_python-0.1.0.dist-info/RECORD
