Metadata-Version: 2.1
Name: mailtm-python
Version: 0.1.0
Summary: A Python SDK for interacting with the Mail.tm API
Home-page: https://github.com/viperadnan-git/mailtm-python-sdk
Author: Adnan Ahmad
Author-email: viperadnan@gmail.com
License: GPLv3
Classifier: Programming Language :: Python :: 3
Classifier: License :: OSI Approved :: GNU General Public License v3 (GPLv3)
Classifier: Operating System :: OS Independent
Requires-Python: >=3.6
License-File: LICENSE
Requires-Dist: requests
